CHANGELOG.md
LICENSE
MANIFEST.in
README.md
setup.cfg
setup.py
sonycam/__init__.py
sonycam/ssdp.py
sonycam/version.py
sonycam.egg-info/PKG-INFO
sonycam.egg-info/SOURCES.txt
sonycam.egg-info/dependency_links.txt
sonycam.egg-info/requires.txt
sonycam.egg-info/top_level.txt