Metadata-Version: 2.1
Name: sonycam
Version: 0.1.0
Summary: Interfacing Sony cameras featuring the Sony Camera Remote API
Home-page: https://gitlab.com/tue-umphy/co2mofetten/python3-sonycam
Author: Yann Buechau
Author-email: nobodyinperson@gmx.de
License: GPLv3
Keywords: sony,camera,remote,api
Platform: UNKNOWN
Classifier: License :: OSI Approved :: GNU General Public License v3 (GPLv3)
